ternausnet/__init__.py
ternausnet/models.py
ternausnet-0.0.1.dist-info/LICENSE
ternausnet-0.0.1.dist-info/METADATA
ternausnet-0.0.1.dist-info/WHEEL
ternausnet-0.0.1.dist-info/top_level.txt
ternausnet-0.0.1.dist-info/RECORD
